{
  "$schema": "http://json-schema.org/draft-07/schema#",
  "properties": {
    "answers": {
      "default": null,
      "items": {
        "items": {
          "type": "string"
        },
        "type": "array"
      },
      "type": [
        "array",
        "null"
      ]
    },
    "cancel": {
      "default": null,
      "type": [
        "boolean",
        "null"
      ]
    },
    "requestId": {
      "type": "string"
    },
    "threadId": {
      "default": null,
      "type": [
        "string",
        "null"
      ]
    }
  },
  "required": [
    "requestId"
  ],
  "title": "ClarifyRespondParams",
  "type": "object"
}
